<?xml version="1.0"?>
<ownershipDocument>

    <schemaVersion>X0508</schemaVersion>

    <documentType>4</documentType>

    <periodOfReport>2025-08-29</periodOfReport>

    <issuer>
        <issuerCik>0000820313</issuerCik>
        <issuerName>AMPHENOL CORP /DE/</issuerName>
        <issuerTradingSymbol>APH</issuerTradingSymbol>
    </issuer>

    <reportingOwner>
        <reportingOwnerId>
            <rptOwnerCik>0001276468</rptOwnerCik>
            <rptOwnerName>WALTER LUC</rptOwnerName>
        </reportingOwnerId>
        <reportingOwnerAddress>
            <rptOwnerStreet1>C/O AMPHENOL CORPORATION</rptOwnerStreet1>
            <rptOwnerStreet2>358 HALL AVENUE</rptOwnerStreet2>
            <rptOwnerCity>WALLINGFORD</rptOwnerCity>
            <rptOwnerState>CT</rptOwnerState>
            <rptOwnerZipCode>06492</rptOwnerZipCode>
            <rptOwnerStateDescription></rptOwnerStateDescription>
        </reportingOwnerAddress>
        <reportingOwnerRelationship>
            <isOfficer>1</isOfficer>
            <officerTitle>President, HES Division</officerTitle>
        </reportingOwnerRelationship>
    </reportingOwner>

    <aff10b5One>0</aff10b5One>

    <nonDerivativeTable>
        <nonDerivativeTransaction>
            <securityTitle>
                <value>Class A Common Stock</value>
            </securityTitle>
            <transactionDate>
                <value>2025-08-29</value>
            </transactionDate>
            <transactionCoding>
                <transactionFormType>4</transactionFormType>
                <transactionCode>G</transactionCode>
                <equitySwapInvolved>0</equitySwapInvolved>
            </transactionCoding>
            <transactionTimeliness></transactionTimeliness>
            <transactionAmounts>
                <transactionShares>
                    <value>18048</value>
                </transactionShares>
                <transactionPricePerShare>
                    <footnoteId id="F1"/>
                </transactionPricePerShare>
                <transactionAcquiredDisposedCode>
                    <value>D</value>
                </transactionAcquiredDisposedCode>
            </transactionAmounts>
            <postTransactionAmounts>
                <sharesOwnedFollowingTransaction>
                    <value>433742</value>
                </sharesOwnedFollowingTransaction>
            </postTransactionAmounts>
            <ownershipNature>
                <directOrIndirectOwnership>
                    <value>D</value>
                </directOrIndirectOwnership>
            </ownershipNature>
        </nonDerivativeTransaction>
    </nonDerivativeTable>

    <footnotes>
        <footnote id="F1">Price of shares when gifted was $110.81.</footnote>
    </footnotes>

    <ownerSignature>
        <signatureName>/s/ Lance E. D'Amico, POA</signatureName>
        <signatureDate>2025-09-02</signatureDate>
    </ownerSignature>
</ownershipDocument>
